README.md
setup.cfg
setup.py
RpyServo/RpyServo.py
RpyServo/__init__.py
RpyServo.egg-info/PKG-INFO
RpyServo.egg-info/SOURCES.txt
RpyServo.egg-info/dependency_links.txt
RpyServo.egg-info/requires.txt
RpyServo.egg-info/top_level.txt