Metadata-Version: 1.0
Name: RpyServo
Version: 0.101
Summary: An easy way to manage servos in a RPi
Home-page: https://github.com/marceloquesada/RpyServo
Author: Marcelo Quesada
Author-email: m.mergulhao@aluno.ufabc.edu.br
License: UNKNOWN
Platform: UNKNOWN
